Assignments/Assignment_5/vending_machine.v
module vending_machine(
    input clk,rst,coin_in,cancel,dispense,
    output reg item_out
);

localparam [2:0] IDLE = 3'b0,READY = 3'b001,DISPENSE = 3'b011;

reg [1:0] ps,ns;

reg [2:0] count;

always @(posedge clk,posedge rst) begin
    if (rst) begin
        ps <= IDLE;
        count <= 0;
    end
    else begin
        ps <= ns;
    end
end

always @(posedge clk,posedge rst) begin
    if (ps == IDLE && coin_in)
        count <= count + 1;
    
    if (cancel || ps == DISPENSE)
        count <= 0;
end


always @(*) begin
    case (ps)
        IDLE: ns = (cancel)? IDLE : ((coin_in && count >= 4)? READY :IDLE); 
        READY:begin ns = (dispense)? DISPENSE : READY; if (cancel) ns = IDLE; end
        DISPENSE:ns = IDLE; 
        default: ns = IDLE;
    endcase
end
always @(*) begin
    if (ps == DISPENSE)
        item_out = 1'b1;
    else
        item_out = 1'b0;
end

endmodule

Assignments/Assignment_5/tb_VM.v
module vending_fsm_tb;

// Inputs
reg clk;
reg rst;
reg coin_in;
reg cancel;
reg dispense;

// Output
wire item_out;

// DUT instantiation
vending_machine dut (
    .clk(clk),
    .rst(rst),
    .coin_in(coin_in),
    .cancel(cancel),
    .dispense(dispense),
    .item_out(item_out)
);

// Clock generation
initial clk = 0;
always #5 clk = ~clk;  // 10ns period --> 50MHz

integer count = 0;

// Test sequence
initial begin
    $display("Starting Vending FSM testbench...");
    $dumpfile("vending_fsm.vcd");
    $dumpvars(0, vending_fsm_tb);

    // Initialize signals
    rst = 1;
    coin_in = 0;
    cancel = 0;
    dispense = 0;

    #12;  // wait for reset
    rst = 0;

    // Insert 2 coins (one per cycle)
    repeat (2) begin
        coin_in = 1;
        count = count + 1;
        #10;
        coin_in = 0;
        #10;
    end

    // Try dispensing
    dispense = 1;
    #10;
    dispense = 0;
    #10;

    // Insert 3 coins (one per cycle)
    repeat (3) begin
        coin_in = 1;
        count = count + 1;

        #10;
        coin_in = 0;
        #10;
    end

    // Try dispensing
    dispense = 1;
    #10;
    dispense = 0;
    #10;

    // Wait and see item_out
    #20;

    // Insert 2 more coins
    repeat (2) begin
        coin_in = 1;

        count = count + 1;

        #10;
        coin_in = 0;
        #10;
    end

    // Cancel transaction
    cancel = 1;
    #10;
    cancel = 0;

    // Wait and observe
    #20;

    $display("Test completed.");
    $stop;
end

initial begin
  $monitor ("Count = %d\tItem out = %b",count,item_out);
end

endmodule

Assignments/Assignment_5/vending_fsm.vcd
$date
	Thu Jul 17 00:44:48 2025
$end
$version
	ModelSim Version 2020.1
$end
$timescale
	1ps
$end

$scope module vending_fsm_tb $end
$var reg 1 ! clk $end
$var reg 1 " rst $end
$var reg 1 # coin_in $end
$var reg 1 $ cancel $end
$var reg 1 % dispense $end
$var wire 1 & item_out $end
$var integer 32 ' count $end

$scope module dut $end
$var parameter 3 ( IDLE $end
$var parameter 3 ) READY $end
$var parameter 3 * DISPENSE $end
$var wire 1 + clk $end
$var wire 1 , rst $end
$var wire 1 - coin_in $end
$var wire 1 . cancel $end
$var wire 1 / dispense $end
$var reg 1 0 item_out $end
$var reg 2 1 ps [1:0] $end
$var reg 2 2 ns [1:0] $end
$var reg 3 3 count [2:0] $end
$upscope $end
$upscope $end
$enddefinitions $end
#0
$dumpvars
0!
1"
0#
0$
0%
00
b0 1
b0 2
b0 3
b0 (
b1 )
b11 *
b0 '
0&
0/
0.
0-
1,
0+
$end
#5
1!
1+
#10
0!
0+
#12
0"
1#
b1 '
0,
1-
#15
1!
1+
b1 3
#20
0!
0+
#22
0#
0-
#25
1!
1+
#30
0!
0+
#32
1#
b10 '
1-
#35
1!
1+
b10 3
#40
0!
0+
#42
0#
0-
#45
1!
1+
#50
0!
0+
#52
1%
1/
#55
1!
1+
#60
0!
0+
#62
0%
0/
#65
1!
1+
#70
0!
0+
#72
1#
b11 '
1-
#75
1!
1+
b11 3
#80
0!
0+
#82
0#
0-
#85
1!
1+
#90
0!
0+
#92
1#
b100 '
1-
#95
1!
1+
b100 3
b1 2
#100
0!
0+
#102
0#
0-
b0 2
#105
1!
1+
#110
0!
0+
#112
1#
b101 '
1-
b1 2
#115
1!
1+
b1 1
b101 3
#120
0!
0+
#122
0#
0-
#125
1!
1+
#130
0!
0+
#132
1%
1/
b11 2
#135
1!
1+
b11 1
b0 2
10
1&
#140
0!
0+
#142
0%
0/
#145
1!
1+
b0 1
b0 3
00
0&
#150
0!
0+
#155
1!
1+
#160
0!
0+
#165
1!
1+
#170
0!
0+
#172
1#
b110 '
1-
#175
1!
1+
b1 3
#180
0!
0+
#182
0#
0-
#185
1!
1+
#190
0!
0+
#192
1#
b111 '
1-
#195
1!
1+
b10 3
#200
0!
0+
#202
0#
0-
#205
1!
1+
#210
0!
0+
#212
1$
1.
#215
1!
1+
b0 3
#220
0!
0+
#222
0$
0.
